cloudwatch_metrics_mcp_server/__init__.py
cloudwatch_metrics_mcp_server/main.py
cloudwatch_metrics_mcp_server-0.1.1.dist-info/METADATA
cloudwatch_metrics_mcp_server-0.1.1.dist-info/WHEEL
cloudwatch_metrics_mcp_server-0.1.1.dist-info/entry_points.txt
cloudwatch_metrics_mcp_server-0.1.1.dist-info/top_level.txt
cloudwatch_metrics_mcp_server-0.1.1.dist-info/RECORD
