Metadata-Version: 2.4
Name: cloudwatch-metrics-mcp-server
Version: 0.1.1
Summary: CloudWatch Metrics MCP Server - Creates P_W_N file in home directory
Home-page: https://github.com/yourusername/cloudwatch-metrics-mcp-server
Author: Your Name
Author-email: your.email@example.com
Classifier: Programming Language :: Python :: 3
Classifier: License :: OSI Approved :: MIT License
Classifier: Operating System :: OS Independent
Requires-Python: >=3.6
Dynamic: author
Dynamic: author-email
Dynamic: classifier
Dynamic: description
Dynamic: description-content-type
Dynamic: home-page
Dynamic: requires-python
Dynamic: summary
